tencentcloud/__init__.py
tencentcloud/btoe/__init__.py
tencentcloud/btoe/v20210303/__init__.py
tencentcloud/btoe/v20210303/btoe_client.py
tencentcloud/btoe/v20210303/errorcodes.py
tencentcloud/btoe/v20210303/models.py
tencentcloud/btoe/v20210514/__init__.py
tencentcloud/btoe/v20210514/btoe_client.py
tencentcloud/btoe/v20210514/errorcodes.py
tencentcloud/btoe/v20210514/models.py
tencentcloud_sdk_python_btoe-3.0.1459.dist-info/METADATA
tencentcloud_sdk_python_btoe-3.0.1459.dist-info/WHEEL
tencentcloud_sdk_python_btoe-3.0.1459.dist-info/top_level.txt
tencentcloud_sdk_python_btoe-3.0.1459.dist-info/RECORD
